{
    "full_text": "",
    "name": "S.R. Crown Hall",
    "picture_urls": [
        [
            "http://www.mimoa.eu/images/5804_l.jpg",
            0
        ],
        [
            "https://readtiger.com/img/wkp/en/Crown_Hall_1.jpg",
            1
        ],
        [
            "https://upload.wikimedia.org/wikipedia/commons/thumb/a/a5/S.R._Crown_Hall.jpg/1200px-S.R._Crown_Hall.jpg",
            2
        ],
        [
            "https://upload.wikimedia.org/wikipedia/commons/e/eb/Crown_Hall_Entrance_060514.jpg",
            3
        ],
        [
            "https://ahughessystemssitesbuilding2014.files.wordpress.com/2014/09/crown-hall-facade.jpg",
            4
        ]
    ],
    "state": "Illinois",
    "summary": "",
    "url": ""
}